sweetlog/__init__.py
sweetlog/datatypes.py
sweetlog/logger.py
sweetlog/streams.py
sweetlog-0.1.2.dist-info/METADATA
sweetlog-0.1.2.dist-info/WHEEL
sweetlog-0.1.2.dist-info/licenses/LICENSE
sweetlog-0.1.2.dist-info/RECORD
